[
  {
    "id": 1,
    "image": "/assets/banner.png",
    "date": "September 1, 2023",
    "title": "Top 10 E-Bikes for Urban Commuters",
    "slug": "top-10-ebikes-for-urban-commuters",
    "tags": [ "Commuting"]
  },
  {
    "id": 2,
    "image": "/assets/banner.png",
    "date": "September 2, 2023",
    "title": "How E-Bikes Are Revolutionizing Transportation",
    "slug": "how-ebikes-are-revolutionizing-transportation",
    "tags": [ "Commuting"]
  },
  {
    "id": 3,
    "image": "/assets/banner.png",
    "date": "September 3, 2023",
    "title": "Choosing the Right E-Bike for Your Needs",
    "slug": "choosing-the-right-ebike",
    "tags": [ "Buying Guide"]
  },
  {
    "id": 4,
    "image": "/assets/banner.png",
    "date": "September 4, 2023",
    "title": "E-Bike Maintenance Tips for Longevity",
    "slug": "ebike-maintenance-tips",
    "tags": [ "Commuting"]
  },
  {
    "id": 5,
    "image": "/assets/banner.png",
    "date": "September 5, 2023",
    "title": "The Environmental Benefits of E-Bikes",
    "slug": "environmental-benefits-of-ebikes",
    "tags": [ "Environment"]
  },
  {
    "id": 6,
    "image": "/assets/banner.png",
    "date": "September 6, 2023",
    "title": "Exploring the Best E-Bike Trails",
    "slug": "best-ebike-trails",
    "tags": [ "Travel"]
  },
  {
    "id": 7,
    "image": "/assets/banner.png",
    "date": "September 7, 2023",
    "title": "E-Bike vs. Traditional Bike: Which is Better?",
    "slug": "ebike-vs-traditional-bike",
    "tags": [ "Comparison"]
  },
  {
    "id": 8,
    "image": "/assets/banner.png",
    "date": "September 8, 2023",
    "title": "Safety Tips for Riding E-Bikes",
    "slug": "safety-tips-for-ebikes",
    "tags": [ "Commuting"]
  },
  {
    "id": 9,
    "image": "/assets/banner.png",
    "date": "September 9, 2023",
    "title": "The Future of E-Bike Technology",
    "slug": "future-of-ebike-technology",
    "tags": [ "Technology"]
  },
  {
    "id": 10,
    "image": "/assets/banner.png",
    "date": "September 10, 2023",
    "title": "How to Improve Your E-Bike Range",
    "slug": "improve-ebike-range",
    "tags": [ "Performance"]
  },
  {
    "id": 11,
    "image": "/assets/banner.png",
    "date": "September 11, 2023",
    "title": "E-Bikes for Fitness: Benefits and Tips",
    "slug": "ebikes-for-fitness",
    "tags": [ "Commuting"]
  },
  {
    "id": 12,
    "image": "/assets/banner.png",
    "date": "September 12, 2023",
    "title": "Best Accessories for Your E-Bike",
    "slug": "best-accessories-for-ebikes",
    "tags": [ "Accessories"]
  },
  {
    "id": 13,
    "image": "/assets/banner.png",
    "date": "September 13, 2023",
    "title": "E-Bikes and Their Impact on Urban Mobility",
    "slug": "ebikes-impact-on-urban-mobility",
    "tags": [ "Mobility"]
  },
  {
    "id": 14,
    "image": "/assets/banner.png",
    "date": "September 14, 2023",
    "title": "E-Bikes for Seniors: A Comprehensive Guide",
    "slug": "ebikes-for-seniors",
    "tags": [ "Seniors"]
  },
  {
    "id": 15,
    "image": "/assets/banner.png",
    "date": "September 15, 2023",
    "title": "Understanding E-Bike Laws and Regulations",
    "slug": "understanding-ebike-laws",
    "tags": [ "Commuting"]
  },
  {
    "id": 16,
    "image": "/assets/banner.png",
    "date": "September 16, 2023",
    "title": "The Best E-Bikes for Off-Road Adventures",
    "slug": "best-ebikes-for-off-road",
    "tags": [ "Off-Road"]
  },
  {
    "id": 17,
    "image": "/assets/banner.png",
    "date": "September 17, 2023",
    "title": "How to Choose an E-Bike for Commuting",
    "slug": "choose-ebike-for-commuting",
    "tags": [ "Commuting"]
  },
  {
    "id": 18,
    "image": "/assets/banner.png",
    "date": "September 18, 2023",
    "title": "E-Bikes and Their Role in Sustainable Transportation",
    "slug": "ebikes-sustainable-transportation",
    "tags": [ "Sustainability"]
  },
  {
    "id": 19,
    "image": "/assets/banner.png",
    "date": "September 19, 2023",
    "title": "The Best E-Bike Brands in 2023",
    "slug": "best-ebike-brands-2023",
    "tags": [ "Brands"]
  },
  {
    "id": 20,
    "image": "/assets/banner.png",
    "date": "September 20, 2023",
    "title": "E-Bike Rentals: What You Need to Know",
    "slug": "ebike-rentals-what-you-need-to-know",
    "tags": [ "Rentals"]
  },
  {
    "id": 21,
    "image": "/assets/banner.png",
    "date": "September 21, 2023",
    "title": "Customizing Your E-Bike: Tips and Tricks",
    "slug": "customizing-your-ebike",
    "tags": [ "Commuting"]
  },
  {
    "id": 22,
    "image": "/assets/banner.png",
    "date": "September 22, 2023",
    "title": "The Benefits of Using E-Bikes for Delivery Services",
    "slug": "benefits-of-ebikes-for-delivery",
    "tags": [ "Delivery"]
  },
  {
    "id": 23,
    "image": "/assets/banner.png",
    "date": "September 23, 2023",
    "title": "How E-Bikes Are Changing the Landscape of Delivery",
    "slug": "ebikes-changing-delivery-landscape",
    "tags": [ "Commuting"]
  },
  {
    "id": 24,
    "image": "/assets/banner.png",
    "date": "September 24, 2023",
    "title": "E-Bikes vs. Cars: A Comparison",
    "slug": "ebikes-vs-cars",
    "tags": [ "Comparison"]
  },
  {
    "id": 25,
    "image": "/assets/banner.png",
    "date": "September 25, 2023",
    "title": "The Future of E-Bikes: Trends to Watch",
    "slug": "future-of-ebikes-trends",
    "tags": [ "Commuting"]
  }
]
